README.md
setup.py
PhilippeCantrelle2ADatavizAutreAvecCarte.egg-info/PKG-INFO
PhilippeCantrelle2ADatavizAutreAvecCarte.egg-info/SOURCES.txt
PhilippeCantrelle2ADatavizAutreAvecCarte.egg-info/dependency_links.txt
PhilippeCantrelle2ADatavizAutreAvecCarte.egg-info/top_level.txt
philcantrel/Data_viz_a_packager_propre.py
philcantrel/__init__.py
philcantrel/module_carte.py
philcantrel/test_graphe_version_py.py